{
  "debug_path": "/data/repo/SIMFormer/data/SIM-simulation/curve/light_pattern_period/standard/train/0.tif",
  "crop_record": {
    "h0": 109,
    "w0": 126,
    "h": 80,
    "w": 80,
    "ref_shape": [
      9,
      256,
      256
    ],
    "scales": [
      1,
      6,
      6
    ]
  },
  "rec_vs_input": {
    "mse": 0.14210082590579987,
    "mae": 0.27555781602859497,
    "psnr": 8.474033673349616
  },
  "psf_debug": {
    "tv": 2.8126831239205785e-05,
    "center_loss": 1.378710294375196e-06,
    "gauss_prior": 3.3086562325479463e-06,
    "center_of_mass": {
      "cy": 23.99884796142578,
      "cx": 24.000226974487305,
      "target_y": 24.0,
      "target_x": 24.0
    },
    "shape": [
      1,
      1,
      1,
      49,
      49
    ]
  },
  "lp_debug": {
    "tv": 0.0014062849804759026,
    "shape": [
      1,
      1,
      9,
      240,
      240
    ]
  },
  "uncertainty_mc": null,
  "saved_files": {
    "sample_npz": "sample.npz",
    "input_rec_train": "input_rec_train.png",
    "input_rec_pct": "input_rec_pct.png",
    "light_pattern": "light_pattern.png",
    "emitter_psf_gauss": "emitter_psf_gauss.png",
    "mask_png": "mask.png",
    "deconv_png": "deconv.png"
  }
}